{
  "entries": [
    {
      "patterns": [
        "heb je een app",
        "is er een app",
        "komt er een app",
        "askyellow app",
        "mobile app askyellow"
      ],
      "category": "shop",
      "lang": "nl",
      "answer": "Een AskYellow-app staat zeker op de planning! 📱💛 We willen alles uiteindelijk nog makkelijker en sneller maken, ook voor onderweg."
    },
    {
      "patterns": [
        "wat zijn de verzendkosten",
        "verzending",
        "shipping cost",
        "hoeveel kost verzending"
      ],
      "category": "shop",
      "lang": "nl",
      "answer": "We hebben regelmatig acties met gratis verzending! Het actuele verzendbeleid vind je altijd op de webshop — maar ik kan je er ook bij helpen als je iets specifieks zoekt. 😊"
    },
    {
      "patterns": [
        "kan ik retourneren",
        "hoe werkt retour",
        "retourbeleid",
        "terugsturen"
      ],
      "category": "shop",
      "lang": "nl",
      "answer": "Natuurlijk! Je kunt binnen de gestelde termijn retourneren. Het proces is simpel en duidelijk uitgelegd op de webshop — en ik help je graag als je er even doorheen wilt. 💛"
    }
  ]
}
